py_whoare/__init__.py
py_whoare-0.1.1.dist-info/LICENSE
py_whoare-0.1.1.dist-info/METADATA
py_whoare-0.1.1.dist-info/WHEEL
py_whoare-0.1.1.dist-info/top_level.txt
py_whoare-0.1.1.dist-info/RECORD
