Metadata-Version: 2.1
Name: py-whoare
Version: 0.1.1
Summary: A Python library for performing WHOIS queries on multiple domains.
Home-page: https://github.com/engjellavdiu/py-whoare
Author: Engjell Avdiu
Author-email: engjellavdiu01@gmail.com
Classifier: Programming Language :: Python :: 3
Classifier: License :: OSI Approved :: MIT License
Classifier: Operating System :: OS Independent
License-File: LICENSE
Requires-Dist: requests
Requires-Dist: aiohttp
